{
	"info": {
		"_postman_id": "a2fca47f-a636-4f3f-bc5f-ded53462a91f",
		"name": "Odoo",
		"schema": "https://schema.getpostman.com/json/collection/v2.1.0/collection.json"
	},
	"item": [
		{
			"name": "Orders",
			"item": [
				{
					"name": "Pull Orders",
					"request": {
						"method": "GET",
						"header": [
							{
								"key": "AuthorizationToken",
								"value": "{{token}}",
								"type": "default"
							}
						],
						"url": {
							"raw": "https://{{domain}}/api/v1/order/pull-orders?limit=1",
							"protocol": "https",
							"host": [
								"{{domain}}"
							],
							"path": [
								"api",
								"v1",
								"order",
								"pull-orders"
							],
							"query": [
								{
									"key": "limit",
									"value": "1"
								}
							]
						}
					},
					"response": []
				},
				{
					"name": "Bulk Update Order status",
					"request": {
						"method": "POST",
						"header": [
							{
								"key": "AuthorizationToken",
								"value": "{{token}}",
								"type": "default"
							}
						],
						"body": {
							"mode": "raw",
							"raw": "[\n    {\n        \"status\": \"synced\",\n        \"hashed_id\": \"31387392471\"\n    }\n    // ,\n    // {\n    //     \"status\": \"approved\",\n    //     \"hashed_id\": \"568058982471\"\n    // }\n    // ,\n    // {\n    //     \"status\": \"delivered\",\n    //     \"hashed_id\": \"______\",\n    //     \"retailer_otp\": \"123456\"\n    // }\n]",
							"options": {
								"raw": {
									"language": "json"
								}
							}
						},
						"url": {
							"raw": "https://{{domain}}/api/v1/order/update-order-status",
							"protocol": "https",
							"host": [
								"{{domain}}"
							],
							"path": [
								"api",
								"v1",
								"order",
								"update-order-status"
							]
						}
					},
					"response": []
				},
				{
					"name": "Bulk Update Order products",
					"request": {
						"method": "POST",
						"header": [
							{
								"key": "AuthorizationToken",
								"value": "{{token}}",
								"type": "default"
							}
						],
						"body": {
							"mode": "raw",
							"raw": "[\n    {\n        \"hashed_id\": \"31387392471\",\n        \"order_details\": [\n            {\n                \"id\": 11988950,\n                \"amount\": 5.0\n            },\n            {//cancelling an order detail\n                \"id\": 11988951,\n                \"cancelled\": true\n            },\n            {//adding an order detail\n                \"internal_product_id\": \"104\",\n                \"amount\": 4.0,\n                \"price\": 320\n            }\n        ]\n    }\n]",
							"options": {
								"raw": {
									"language": "json"
								}
							}
						},
						"url": {
							"raw": "https://{{domain}}/api/v1/order/update-order-details",
							"protocol": "https",
							"host": [
								"{{domain}}"
							],
							"path": [
								"api",
								"v1",
								"order",
								"update-order-details"
							]
						}
					},
					"response": []
				}
			]
		},
		{
			"name": "Products",
			"item": [
				{
					"name": "List supplier products",
					"request": {
						"method": "GET",
						"header": [
							{
								"key": "AuthorizationToken",
								"value": "{{token}}",
								"type": "default"
							}
						],
						"url": {
							"raw": "https://{{domain}}/api/v1/supplier-product?page=1&per_page=100",
							"protocol": "https",
							"host": [
								"{{domain}}"
							],
							"path": [
								"api",
								"v1",
								"supplier-product"
							],
							"query": [
								{
									"key": "internal_product_id",
									"value": "104",
									"disabled": true
								},
								{
									"key": "page",
									"value": "1"
								},
								{
									"key": "per_page",
									"value": "100"
								}
							]
						}
					},
					"response": []
				},
				{
					"name": "Update supplier products",
					"request": {
						"method": "POST",
						"header": [
							{
								"key": "AuthorizationToken",
								"value": "{{token}}",
								"type": "default"
							}
						],
						"body": {
							"mode": "raw",
							"raw": "[\n  {\n    \"internal_product_id\": \"103\",\n    \"min_order\": 1,\n    \"max_order\": 20,\n    \"in_stock\": true,\n    \"is_published\": true\n  },\n  {\n    \"internal_product_id\": \"100\",\n    \"min_order\": 1,\n    \"max_order\": 10,\n    \"available_stock_quantity\": 10000,\n    \"in_stock\": false,\n    \"is_published\": false\n  },\n  {\n    \"internal_product_id\": \"109\",\n    \"min_order\": 1,\n    \"max_order\": 10,\n    \"available_stock_quantity\": 10000,\n    \"in_stock\": true,\n    \"is_published\": false\n  }\n]",
							"options": {
								"raw": {
									"language": "json"
								}
							}
						},
						"url": {
							"raw": "https://{{domain}}/api/v1/supplier-product/bulk-update",
							"protocol": "https",
							"host": [
								"{{domain}}"
							],
							"path": [
								"api",
								"v1",
								"supplier-product",
								"bulk-update"
							]
						}
					},
					"response": []
				}
			]
		},
		{
			"name": "Base Products",
			"item": [
				{
					"name": "List base products",
					"request": {
						"method": "GET",
						"header": [
							{
								"key": "AuthorizationToken",
								"value": "{{token}}",
								"type": "default"
							}
						],
						"url": {
							"raw": "https://{{domain}}/api/v1/supplier-product/base-products?page=6&per_page=100",
							"protocol": "https",
							"host": [
								"{{domain}}"
							],
							"path": [
								"api",
								"v1",
								"supplier-product",
								"base-products"
							],
							"query": [
								{
									"key": "base_product_id",
									"value": "3800",
									"disabled": true
								},
								{
									"key": "page",
									"value": "6"
								},
								{
									"key": "per_page",
									"value": "100"
								},
								{
									"key": "search_token",
									"value": "أيزيس أعشاب",
									"disabled": true
								}
							]
						}
					},
					"response": []
				},
				{
					"name": "Update base products",
					"request": {
						"method": "POST",
						"header": [
							{
								"key": "AuthorizationToken",
								"value": "{{token}}",
								"type": "default"
							}
						],
						"body": {
							"mode": "raw",
							"raw": "[\n    {\n        // \"supplier_product_id\": 480,\n        // \"internal_product_id\": \"149\",\n        \"base_product_id\": 8,\n        \"unit\": \"box\",\n        \"unit_count\": 12,\n        \"in_stock\": true,\n        \"is_bundle\": false,\n        \"is_published\": false,\n        \"max_order\": 10,\n        \"available_stock_quantity\": 40\n    }\n    // ,\n    // { // intended to generate error\n    //     \"supplier_product_id\": 480,\n    //     \"available_stock_quantity\": -40\n    // }\n]",
							"options": {
								"raw": {
									"language": "json"
								}
							}
						},
						"url": {
							"raw": "https://{{domain}}/api/v1/supplier-product/base-product/bulk-update",
							"protocol": "https",
							"host": [
								"{{domain}}"
							],
							"path": [
								"api",
								"v1",
								"supplier-product",
								"base-product",
								"bulk-update"
							]
						}
					},
					"response": []
				},
				{
					"name": "Update base products stock (across all units)",
					"request": {
						"method": "POST",
						"header": [
							{
								"key": "AuthorizationToken",
								"value": "{{token}}",
								"type": "default"
							}
						],
						"body": {
							"mode": "raw",
							"raw": "[\n    { \n        \"base_product_id\": 4090,\n        \"available_stock_quantity\": 300\n    }\n]",
							"options": {
								"raw": {
									"language": "json"
								}
							}
						},
						"url": {
							"raw": "https://{{domain}}/api/v1/supplier-product/base-product/bulk-update-stock",
							"protocol": "https",
							"host": [
								"{{domain}}"
							],
							"path": [
								"api",
								"v1",
								"supplier-product",
								"base-product",
								"bulk-update-stock"
							]
						}
					},
					"response": []
				}
			]
		}
	],
	"event": [
		{
			"listen": "prerequest",
			"script": {
				"type": "text/javascript",
				"exec": [
					""
				]
			}
		},
		{
			"listen": "test",
			"script": {
				"type": "text/javascript",
				"exec": [
					""
				]
			}
		}
	],
	"variable": [
		{
			"key": "domain",
			"value": "supplier-integrations.cartona.space"
		},
		{
			"key": "token",
			"value": "eyJhbGciOiJIUzI1NiJ9.eyJzdXBwbGllcl9pbnRlZ3JhdGlvbl9pZCI6MiwiZGF0ZSI6IjIwMjUtMDMtMjVUMjA6MzM6NTQrMDA6MDAifQ.c0GvE47PhAovjvx-WtMWfsUfXPePXF6PgAVOOCys8wM"
		}
	]
}